datetime_interval
