Metadata-Version: 1.1
Name: datetime-interval
Version: 0.2
Summary: A representation of a duration of time
Home-page: https://www.github.com/zeckalpha/datetime-interval
Author: Kyle Marek-Spartz
Author-email: kyle.marek.spartz@gmail.com
License: MIT
Platform: UNKNOWN
Classifier: Development Status :: 3 - Alpha
Classifier: Intended Audience :: Developers
Classifier: License :: OSI Approved :: MIT License
Classifier: Topic :: Software Development :: Libraries :: Python Modules
Classifier: Topic :: Utilities
